ai_models_aurora_gfs/__init__.py
ai_models_aurora_gfs/_version.py
ai_models_aurora_gfs/model.py
ai_models_aurora_gfs-0.7.0.dist-info/LICENSE
ai_models_aurora_gfs-0.7.0.dist-info/METADATA
ai_models_aurora_gfs-0.7.0.dist-info/WHEEL
ai_models_aurora_gfs-0.7.0.dist-info/entry_points.txt
ai_models_aurora_gfs-0.7.0.dist-info/top_level.txt
ai_models_aurora_gfs-0.7.0.dist-info/RECORD
