Metadata-Version: 2.1
Name: ai-models-aurora-gfs
Version: 0.7.0
Summary: An ai-models plugin to run Microsoft's Aurora model
Author-email: Jacob Radford <jacob.radford@noaa.gov>
License: Apache License
Project-URL: Repository, https://github.com/jacob-radford/ai-models-aurora-gfs
Keywords: ai,tools
Classifier: Development Status :: 4 - Beta
Classifier: Intended Audience :: Developers
Classifier: License :: OSI Approved :: Apache Software License
Classifier: Operating System :: OS Independent
Classifier: Programming Language :: Python :: 3 :: Only
Classifier: Programming Language :: Python :: 3.9
Classifier: Programming Language :: Python :: 3.10
Classifier: Programming Language :: Python :: 3.11
Classifier: Programming Language :: Python :: 3.12
Classifier: Programming Language :: Python :: Implementation :: CPython
Classifier: Programming Language :: Python :: Implementation :: PyPy
Requires-Python: >=3.10
License-File: LICENSE
Requires-Dist: microsoft-aurora >=1.1.0
Requires-Dist: ai-models-gfs
Provides-Extra: dev
Requires-Dist: pre-commit ; extra == 'dev'
